madsci/client/__init__.py
madsci/client/client_mixin.py
madsci/client/data_client.py
madsci/client/event_client.py
madsci/client/experiment_client.py
madsci/client/lab_client.py
madsci/client/location_client.py
madsci/client/node/__init__.py
madsci/client/node/abstract_node_client.py
madsci/client/node/rest_node_client.py
madsci/client/resource_client.py
madsci/client/workcell_client.py
madsci_client-0.6.1.dist-info/METADATA
madsci_client-0.6.1.dist-info/WHEEL
madsci_client-0.6.1.dist-info/entry_points.txt
madsci_client-0.6.1.dist-info/RECORD
